reed_solomon_py-0.1.0.dist-info/METADATA
reed_solomon_py-0.1.0.dist-info/WHEEL
reed_solomon_py/__init__.py
reed_solomon_py/__init__.pyi
reed_solomon_py/py.typed
reed_solomon_py/reed_solomon_py.cp312-win_amd64.pyd
reed_solomon_py-0.1.0.dist-info/RECORD
