Metadata-Version: 2.4
Name: reed_solomon_py
Version: 0.1.0
Summary: python bindings for reed solomon lib
Author: konstantin Gorshkov <kostya_gorshkov_06@vk.com>
Author-email: konstantin Gorshkov <kostya_gorshkov_06@vk.com>
License: MIT
Project-URL: Source Code, https://github.com/kostya2023/reed_solomon_py
